Metadata-Version: 2.1
Name: cdep-package-b
Version: 0.0.1
Summary: Package B of cdep
Home-page: UNKNOWN
Author: John Doe
Author-email: jmartinpe@sia.es
License: UNLICENSED
Platform: UNKNOWN
Classifier: Programming Language :: Python :: 3
